clayer/__init__.py
clayer/py.typed
clayer-0.1.0.dist-info/WHEEL
clayer-0.1.0.dist-info/METADATA
clayer-0.1.0.dist-info/RECORD
